auth_matrix/__init__.py
auth_matrix/admin.py
auth_matrix/admin_urls.py
auth_matrix/admin_views.py
auth_matrix/apps.py
auth_matrix/py.typed
auth_matrix/templates/admin/accounts/user/change_list.html
auth_matrix/templates/admin/auth/group/change_list.html
auth_matrix/templates/admin/auth/user/change_list.html
auth_matrix/templates/admin/authorization/authorization_matrix.html
maykin_auth_matrix-0.1.1.dist-info/LICENSE
maykin_auth_matrix-0.1.1.dist-info/METADATA
maykin_auth_matrix-0.1.1.dist-info/WHEEL
maykin_auth_matrix-0.1.1.dist-info/top_level.txt
maykin_auth_matrix-0.1.1.dist-info/RECORD
