Metadata-Version: 2.1
Name: maykin-auth-matrix
Version: 0.1.1
Summary: TODO
Author-email: Maykin Media <support@maykinmedia.nl>
License: Copyright 2024 Maykin Media
Project-URL: Homepage, https://github.com/maykinmedia/maykin-auth-matrix
Project-URL: Documentation, http://maykin-auth-matrix.readthedocs.io/en/latest/
Project-URL: Bug Tracker, https://github.com/maykinmedia/maykin-auth-matrix/issues
Project-URL: Source Code, https://github.com/maykinmedia/maykin-auth-matrix
Keywords: TODO
Classifier: Development Status :: 3 - Alpha
Classifier: Framework :: Django
Classifier: Framework :: Django :: 4.2
Classifier: Intended Audience :: Developers
Classifier: Operating System :: Unix
Classifier: Operating System :: MacOS
Classifier: Operating System :: Microsoft :: Windows
Classifier: Programming Language :: Python :: 3.10
Classifier: Programming Language :: Python :: 3.11
Classifier: Programming Language :: Python :: 3.12
Classifier: Topic :: Software Development :: Libraries :: Python Modules
Requires-Python: >=3.10
License-File: LICENSE
Requires-Dist: django >=4.2
Requires-Dist: django-import-export
Provides-Extra: docs
Requires-Dist: sphinx ; extra == 'docs'
Requires-Dist: sphinx-rtd-theme ; extra == 'docs'
Provides-Extra: release
Requires-Dist: bump-my-version ; extra == 'release'
Provides-Extra: tests
Requires-Dist: pytest ; extra == 'tests'
Requires-Dist: pytest-django ; extra == 'tests'
Requires-Dist: pytest-cov ; extra == 'tests'
Requires-Dist: tox ; extra == 'tests'
Requires-Dist: isort ; extra == 'tests'
Requires-Dist: black ; extra == 'tests'
Requires-Dist: flake8 ; extra == 'tests'
